{
  "schema": "BP_LOCATION_1.0",
  "location_id": "MSTREETS_001",
  "name": "Miami Streets",
  "display_name": "Miami Streets — South FL Mainland",
  "version": "1.0",
  "created": "2026-03-07",
  "status": "active",
  "lab_compat": [
    "ImageLab",
    "VideoLab",
    "CopyLab",
    "WebLab"
  ],
  "geo": {
    "city": "Miami",
    "state": "FL",
    "country": "US",
    "market": "Miami-Dade",
    "neighborhoods": [
      "Downtown",
      "Brickell",
      "Coconut Grove",
      "Coral Gables corridor",
      "Overtown approach"
    ],
    "primary_zone": "Miami mainland — calles, highways y barrios"
  },
  "zones": [
    {
      "zone_id": "MSTR_Z1",
      "zone_name": "I-95 / Highway Corridor",
      "description": "Autopista I-95 en tramos urbanos con el skyline de Downtown/Brickell de fondo. Múltiples niveles de infraestructura: viaductos, rampas, puentes elevados del Metromover/Metrorail. Vista desde el interior del carro. Ambiente de movimiento urbano, ciudad en expansión constante — grúas de construcción visibles en múltiples tomas. Señales verdes de autopista como elemento gráfico identificador.",
      "subtype": "highway_urban_motion",
      "landmarks_visible": [
        "I-95 South / Downtown exit signs",
        "Rickenbacker Causeway exit (Key Biscayne)",
        "Miami Beach / Airport split sign",
        "Exit 3B NW 8th St / Stadium / Arena",
        "Metromover azul elevado sobre I-95",
        "Overtown / Historic Village signage",
        "Skyline Downtown + Brickell en construcción (múltiples grúas)"
      ],
      "lighting": {
        "natural": {
          "midday": {
            "quality": "dura, cielo azul intenso con nubes cúmulo blancas — alta saturación",
            "color_temp": "5500–6000K",
            "notes": "El concreto de los viaductos absorbe luz cálida. Cielo con nubes genera contraste dramático útil para composición."
          },
          "overcast": {
            "quality": "difusa, neutra, baja en contraste",
            "notes": "Útil como fondo neutro para overlay de texto o producto."
          }
        }
      },
      "color_palette": {
        "dominant": [
          "#D4C9B8 (concreto viaductos)",
          "#87CEEB (cielo Florida)",
          "#FFFFFF (nubes)",
          "#4A5568 (asfalto)"
        ],
        "accent": [
          "#2F855A (vegetación márgenes)",
          "#276749 (señales verdes)",
          "#F6E05E (señales amarillas)",
          "#3182CE (Metromover azul)"
        ],
        "mood_tags": [
          "urbano",
          "en movimiento",
          "expansión",
          "infraestructura",
          "ciudad viva",
          "Miami moderno"
        ]
      },
      "visual_references": [
        {
          "ref_id": "Z1_001",
          "source_file": "IMG_0957.jpeg",
          "description": "Bajo viaducto de I-95: múltiples niveles de rampas de hormigón sobre la autopista. Señal verde 'Overtown / Historic Village' visible a la derecha. Cielo azul entre las estructuras. Vista desde el interior del carro.",
          "time_of_day": "midday",
          "orientation": "vertical",
          "best_use": [
            "motion content",
            "intro de contenido urbano Miami",
            "b-roll dinámico"
          ]
        },
        {
          "ref_id": "Z1_002",
          "source_file": "IMG_0959.jpeg",
          "description": "I-95 acercándose a Downtown: skyline completo al fondo izquierda (edificios en construcción). Tesla blanco y camión en la vía. Cielo azul despejado.",
          "time_of_day": "midday",
          "orientation": "vertical",
          "best_use": [
            "establishing shot ciudad moderna",
            "fondo para claims de presencia en Miami"
          ]
        },
        {
          "ref_id": "Z1_003",
          "source_file": "IMG_0965.jpeg",
          "description": "Vista desde highway: señales verdes 'Miami Ave / Downtown', 'Biscayne Blvd', '95 South / SW 7th St / Brickell Ave'. Skyline a ambos lados. Muy identificable como Miami central.",
          "time_of_day": "midday",
          "orientation": "vertical",
          "best_use": [
            "establishing shot con texto de ciudad legible",
            "geo-tag visual",
            "contexto Miami B2B"
          ]
        },
        {
          "ref_id": "Z1_004",
          "source_file": "IMG_0966.jpeg",
          "description": "Highway vacío con skyline incipiente al fondo. Tesla blanco modelo 3 y pickup. Nubes dispersas sobre azul.",
          "time_of_day": "midday",
          "orientation": "vertical"
        },
        {
          "ref_id": "Z1_005",
          "source_file": "IMG_0982.jpeg",
          "description": "Brickell/Downtown desde highway: múltiples torres de lujo (>30 pisos) y grúas de construcción. Metromover azul elevado en plano medio. Cielo azul intenso.",
          "time_of_day": "midday",
          "orientation": "vertical",
          "best_use": [
            "Brickell como símbolo de crecimiento y poder económico",
            "contexto Neurone B2B",
            "Vizos presencia institucional"
          ]
        },
        {
          "ref_id": "Z1_006",
          "source_file": "IMG_0986.jpeg",
          "description": "Similar al anterior. Mano con anillo visible en esquina (reflejo en vidrio). Mismo tramo de Brickell desde highway.",
          "time_of_day": "midday",
          "orientation": "vertical",
          "note": "Mano con anillo visible — excluir si se usa como fondo limpio"
        },
        {
          "ref_id": "Z1_007",
          "source_file": "IMG_0988.jpeg",
          "description": "Highway con billboard publicitario visible (azul, parcialmente legible). Grúas y torres en construcción al fondo. Nubes dramáticas.",
          "time_of_day": "midday",
          "orientation": "vertical",
          "best_use": [
            "referencia de entorno OOH/billboard",
            "contenido sobre presencia de marca en ciudad"
          ]
        },
        {
          "ref_id": "Z1_008",
          "source_file": "IMG_0991.jpeg",
          "description": "Highway hacia norte con skyline disperso a la derecha. Nubes cúmulo voluminosas. Señal verde de salida visible. Tráfico ligero.",
          "time_of_day": "midday",
          "orientation": "vertical"
        },
        {
          "ref_id": "Z1_009",
          "source_file": "IMG_1013.jpeg",
          "description": "Señal 'Rickenb[acker] Csw / Key Bis[cayne]' en primer plano derecho. Highway hacia norte con torres y vegetación. Cielo con nubes dramáticas.",
          "time_of_day": "midday",
          "orientation": "vertical",
          "best_use": [
            "geo-anchor Key Biscayne / zona premium",
            "establishing para audiencia Miami-Dade"
          ],
          "asset_path": "locations/assets/MiamiStreets/ms_i95_rickenbacker_sign_01.jpeg"
        },
        {
          "ref_id": "Z1_010",
          "source_file": "IMG_0996.jpeg",
          "description": "Carretera elevada con señales 'I-95 South/Downtown' y split hacia 'East Miami Beach / West Airport'. Infraestructura multi-nivel. Camión en vía.",
          "time_of_day": "midday",
          "orientation": "vertical",
          "best_use": [
            "Miami Beach vs mainland — narrativa geográfica",
            "opening de serie de contenido"
          ]
        },
        {
          "ref_id": "Z1_011",
          "source_file": "IMG_1006.jpeg",
          "description": "Bajo puente del Metromover (estructura azul turquesa). Vista frontal hacia horizonte abierto con palmeras y edificios coloridos al fondo (morado, verde). Muy gráfico y arquitectónico.",
          "time_of_day": "midday",
          "orientation": "vertical",
          "best_use": [
            "frame arquitectónico único",
            "b-roll de transición",
            "contenido de ciudad en movimiento"
          ],
          "asset_path": "locations/assets/MiamiStreets/ms_i95_brickell_metromover_01.jpeg"
        },
        {
          "ref_id": "Z1_012",
          "source_file": "IMG_1007.jpeg",
          "description": "Highway con skyline de Downtown en construcción: múltiples grúas, torres en distintos estados. Puentes elevados en cascada. Cielo azul.",
          "time_of_day": "midday",
          "orientation": "vertical",
          "best_use": [
            "metáfora de crecimiento/construcción",
            "Miami como ciudad en expansión"
          ],
          "asset_path": "locations/assets/MiamiStreets/ms_i95_downtown_cranes_01.jpeg"
        },
        {
          "ref_id": "Z1_013",
          "source_file": "IMG_1048.jpeg",
          "description": "I-95 con señal 'Exit 3B / NW 8th St / Stadium / Arena / Next Right'. Múltiples niveles de infraestructura vial. Sky muy azul. Palmeras a la derecha.",
          "time_of_day": "midday",
          "orientation": "vertical",
          "best_use": [
            "geo-anchor Downtown cultural",
            "b-roll de ciudad navegándose"
          ],
          "asset_path": "locations/assets/MiamiStreets/ms_boulevard_palms_wall_01.jpeg"
        },
        {
          "ref_id": "Z1_014",
          "source_file": "IMG_1057.jpeg",
          "asset_path": "locations/assets/MiamiStreets/ms_i95_parkmiami_sign_01.jpeg",
          "description": "I-95 urbana con señal verde 'Park Miami / Miami Beach' overhead. Edificio residencial alto con mural a la derecha. Tráfico liviano. Cielo nublado parcial.",
          "time_of_day": "afternoon",
          "orientation": "vertical",
          "best_use": [
            "establishing shot Miami highway",
            "señalética urbana",
            "motion content dirección Miami Beach"
          ]
        },
        {
          "ref_id": "Z1_015",
          "source_file": "IMG_1049.jpeg",
          "asset_path": "locations/assets/MiamiStreets/ms_boulevard_led_sign_01.jpeg",
          "description": "Bulevar amplio con palmeras reales y muro de piedra (Coral Gables corridor). Panel LED overhead con información de tráfico. Vegetación mixta: palmas + árboles tropicales. Hora dorada.",
          "time_of_day": "golden_hour",
          "orientation": "vertical",
          "best_use": [
            "contexto residencial premium Miami",
            "bulevar con infraestructura",
            "fondo para producto lifestyle"
          ]
        },
        {
          "ref_id": "Z1_016",
          "source_file": "IMG_1052.jpeg",
          "asset_path": "locations/assets/MiamiStreets/ms_i95_skyline_downtown_01.jpeg",
          "description": "I-95 con skyline completo de Downtown Miami al fondo: torre en construcción prominente, múltiples highrise. Cielo azul con nubes cúmulo. Vista panorámica desde el interior del carro.",
          "time_of_day": "afternoon",
          "orientation": "vertical",
          "best_use": [
            "establishing shot ciudad Miami",
            "poder económico y crecimiento",
            "fondo panorámico para claims"
          ]
        },
        {
          "ref_id": "Z1_017",
          "source_file": "IMG_1054.jpeg",
          "asset_path": "locations/assets/MiamiStreets/ms_i95_led_ramp_closure_01.jpeg",
          "description": "I-95 con panel electrónico LED overhead (naranja sobre negro). Tráfico fluido, dos carriles visibles. Torre circular al fondo derecha (Edgewater/Wynwood). Cielo nublado parcial.",
          "time_of_day": "afternoon",
          "orientation": "vertical",
          "best_use": [
            "signage urbano LED",
            "infraestructura vial Miami",
            "b-roll highway con elemento gráfico fuerte"
          ]
        },
        {
          "ref_id": "Z1_018",
          "source_file": "IMG_1055.jpeg",
          "asset_path": "locations/assets/MiamiStreets/ms_i95_biscayne_tower_01.jpeg",
          "description": "I-95 con señal verde 'Biscayne Blvd / Downtown'. Torre cilíndrica residencial dominando el frame derecha (Edgewater). Tráfico múltiple carriles. Cielo dramático con nubes.",
          "time_of_day": "afternoon",
          "orientation": "vertical",
          "best_use": [
            "Downtown exit shot",
            "iconografía Biscayne corridor",
            "establishing shot Edgewater/Wynwood"
          ]
        }
      ],
      "shooting_notes": {
        "type": "todas las tomas desde interior de vehículo en movimiento",
        "best_time": "9:00 AM – 1:00 PM (luz alta, cielo azul Florida característico)",
        "avoid": [
          "horas pico 7-9 AM y 5-7 PM — tráfico denso arruina perspectiva",
          "lluvia (aunque puede usarse para mood dramático)"
        ],
        "legal": "filmación desde vehículo en movimiento en vía pública — no requiere permiso"
      }
    },
    {
      "zone_id": "MSTR_Z2",
      "zone_name": "Brickell / Luxury Towers Street Level",
      "description": "Calles al pie de las torres residenciales de lujo de Brickell. Fachadas de vidrio curvo de >40 pisos, vegetación tropical al nivel de calle, carros de lujo aparcados. Ambiente de poder económico, silencioso y exclusivo.",
      "subtype": "urban_luxury_residential",
      "visual_references": [
        {
          "ref_id": "Z2_001",
          "source_file": "IMG_1030.jpeg",
          "description": "Dos torres de lujo en vidrio gris-azul (posiblemente Brickell o Coconut Grove). Fachadas curvas, sello arquitectónico premium. Lamborghini Urus negro aparcado en primer plano. Vegetación tropical densa y seto. Cielo nublado.",
          "time_of_day": "overcast",
          "orientation": "vertical",
          "best_use": [
            "contexto lujo Miami",
            "setting para Portal Pro B2B Neurone",
            "Vizos institutional premium",
            "fondo para copy de distribución premium"
          ],
          "asset_path": "locations/assets/MiamiStreets/ms_brickell_towers_luxury_01.jpeg"
        }
      ],
      "color_palette": {
        "dominant": [
          "#4A6785 (vidrio torres)",
          "#2D3748 (sombras)",
          "#68D391 (vegetación)",
          "#A0AEC0 (cielo nublado)"
        ],
        "accent": [
          "#1A202C (coche negro)",
          "#F7FAFC (marcos ventanas)"
        ],
        "mood_tags": [
          "lujo silencioso",
          "poder económico",
          "premium B2B",
          "Brickell",
          "exclusivo"
        ]
      }
    },
    {
      "zone_id": "MSTR_Z3",
      "zone_name": "Coconut Grove — Calles con Carácter",
      "description": "El corazón orgánico y bohemio de Miami. Calles arboladas con Ficus y Banyans centenarios formando túneles naturales. El trolley naranja-verde característico del Grove. Marina de botes con almacenamiento en rack. Ambiente tranquilo, residencial-comercial de alto nivel. Muy distinto al resto de Miami.",
      "subtype": "neighborhood_organic",
      "landmarks_visible": [
        "Coconut Grove Trolley (naranja y verde, logo 'THE KEY')",
        "Banyan/Ficus trees gigantes con raíces aéreas",
        "Marina con boat rack storage de múltiples niveles",
        "Arquitectura residencial baja con vegetación exuberante"
      ],
      "lighting": {
        "natural": {
          "filtered_canopy": {
            "quality": "luz filtrada y quebrada por el dosel de árboles — dappled light",
            "color_temp": "4500–5000K con manchas cálidas en franjas de sol directo",
            "notes": "El tunnel de árboles crea luz dramaticamente diferente al resto de Miami. Muy cinematográfico para beauty content."
          },
          "open_marina": {
            "quality": "luz directa lateral, sombras de árboles en primer plano",
            "color_temp": "5500K midday"
          }
        }
      },
      "color_palette": {
        "canopy": {
          "dominant": [
            "#2D6A4F (verde profundo follaje)",
            "#95A97A (amarillo-verde hojas secas)",
            "#8B7355 (corteza troncos)",
            "#D4C5B0 (asfalto con sombras)"
          ],
          "accent": [
            "#FFFFFF (coche de policía)",
            "#F97316 (trolley naranja)",
            "#16A34A (trolley verde)"
          ],
          "mood_tags": [
            "orgánico",
            "bohemio premium",
            "ecológico",
            "tranquilo",
            "íntimo",
            "heritage Miami"
          ]
        },
        "marina": {
          "dominant": [
            "#7CB9E8 (cielo parcial)",
            "#5D8A6B (césped)",
            "#E8DCC8 (botes blancos)",
            "#A0856C (troncos)"
          ],
          "mood_tags": [
            "náutico",
            "lifestyle",
            "fin de semana",
            "aspiracional tranquilo"
          ]
        }
      },
      "visual_references": [
        {
          "ref_id": "Z3_001",
          "source_file": "IMG_1029.jpeg",
          "description": "Coconut Grove Trolley naranja-verde pasando por calle del Grove. Árboles Ficus/Banyan enormes con raíces aéreas visibles. Edificio rosado a la izquierda. Acera de ladrillo. Atmósfera bohemia y tranquila del barrio.",
          "time_of_day": "midday_overcast",
          "orientation": "vertical",
          "best_use": [
            "establishing shot Coconut Grove",
            "contenido de lifestyle local Miami",
            "backdrop para copy sobre comunidad/barrio"
          ],
          "asset_path": "locations/assets/MiamiStreets/ms_coconutgrove_trolley_01.jpeg"
        },
        {
          "ref_id": "Z3_002",
          "source_file": "IMG_1043.jpeg",
          "description": "Calle con palmeras jóvenes y árboles de copa media. Casas blancas a ambos lados, cables de electricidad. Cielo azul con nubes vespertinas. Ambiente residencial tranquilo.",
          "time_of_day": "late_afternoon",
          "orientation": "vertical",
          "best_use": [
            "barrio residencial Miami",
            "lifestyle cotidiano",
            "contenido de calle tranquila"
          ],
          "asset_path": "locations/assets/MiamiStreets/ms_residential_palm_street_01.jpeg"
        },
        {
          "ref_id": "Z3_003",
          "source_file": "IMG_1044.jpeg",
          "description": "Túnel de árboles: canopy completo de live oaks sobre la calle. Coche de policía blanco aparcado. Luz filtrada. Muy orgánico y cinematográfico. Podría ser Old Cutler Road o SW 27th Ave.",
          "time_of_day": "midday",
          "orientation": "vertical",
          "best_use": [
            "túnel natural para transiciones de video",
            "mood íntimo y fresco",
            "beauty content con luz filtrada natural"
          ],
          "asset_path": "locations/assets/MiamiStreets/ms_coconutgrove_oak_tunnel_01.jpeg"
        },
        {
          "ref_id": "Z3_004",
          "source_file": "IMG_1011.jpeg",
          "description": "Bulevar con palmeras reales (royal palms) altas en acera derecha, muro de piedra residencial. Árboles frondosos a la izquierda. Cielo azul-blanco vespertino. Posiblemente Coral Gables o Coconut Grove norte.",
          "time_of_day": "late_afternoon",
          "orientation": "vertical",
          "best_use": [
            "bulevar premium de barrio",
            "lifestyle aspiracional tranquilo",
            "setting para contenido de cabello/belleza al aire libre"
          ],
          "asset_path": "locations/assets/MiamiStreets/ms_boulevard_royal_palms_01.jpeg"
        },
        {
          "ref_id": "Z3_005",
          "source_file": "IMG_1012.jpeg",
          "description": "Marina de Coconut Grove: boat rack de múltiples niveles (4 alturas) con decenas de yates y lanchas almacenadas. Árboles de otoño (hojas amarillas-ocre) en primer plano. Césped verde. Vista trasera.",
          "time_of_day": "midday",
          "orientation": "vertical",
          "best_use": [
            "lifestyle náutico Miami",
            "contexto de riqueza discreta",
            "setting para claims de cliente Premium/Pro"
          ],
          "asset_path": "locations/assets/MiamiStreets/ms_coconutgrove_marina_01.jpeg"
        },
        {
          "ref_id": "Z3_006",
          "source_file": "IMG_1013_marina.jpeg",
          "description": "Misma marina desde ángulo más abierto. Rack de botes visible, palmeras altas, edificio blanco de fondo, jardinería. Césped bien mantenido. Más composición de parque que marina.",
          "time_of_day": "midday",
          "orientation": "vertical",
          "best_use": [
            "establishing shot lifestyle premium Miami waterfront"
          ]
        },
        {
          "ref_id": "Z3_007",
          "source_file": "IMG_1032.jpeg",
          "asset_path": "locations/assets/MiamiStreets/ms_coconutgrove_related_01.jpeg",
          "description": "Edificio Related + Park Grove al fondo (Coconut Grove). Calle con conos naranja, bandera azul, escalinata de piedra, restaurante Park Grove al pie. Banyan trees de fondo. Tráfico tranquilo. Mezcla de construcción premium y Grove orgánico.",
          "orientation": "portrait",
          "time_of_day": "overcast_midday",
          "best_use": [
            "contexto barrio premium en construcción",
            "Coconut Grove como zona en evolución",
            "establishing shot para contenido aspiracional"
          ]
        }
      ],
      "shooting_notes": {
        "best_angles": [
          "nivel de calle bajo los árboles mirando hacia el horizonte",
          "desde acera mirando el trolley",
          "entre los botes en la marina para perspectiva de escala"
        ],
        "best_time": "8:00–10:00 AM (luz baja filtrada por árboles = magia) / 5:00–6:30 PM (luz cálida lateral en bulevar royal palms)",
        "avoid": [
          "mediodía bajo canopy cerrado — muy oscuro sin fill",
          "fin de semana en zona comercial — muy concurrido"
        ],
        "permit_required": false,
        "crowd_level": "bajo entre semana, moderado fin de semana"
      }
    }
  ],
  "meta_tags": [
    "miami_streets",
    "miami_mainland",
    "i95",
    "brickell",
    "downtown",
    "coconut_grove",
    "coral_gables",
    "highway",
    "urban",
    "motion",
    "luxury",
    "neighborhood",
    "florida",
    "ES-FL",
    "neurone_cosmetics_compatible",
    "vizos_compatible"
  ],
  "brand_compatibility": {
    "neurone_cosmetics": {
      "zones": [
        "MSTR_Z3"
      ],
      "recommended_time": [
        "late_afternoon",
        "filtered_canopy_morning"
      ],
      "tone_match": "Lifestyle orgánico/aspiracional — Coconut Grove encaja con cliente Neurone B2C Miami",
      "copy_anchors": [
        "el barrio que cuida lo que come y lo que se pone",
        "your neighborhood, your ritual",
        "hecho para el Miami que no necesita gritarlo"
      ]
    },
    "vizos_cosmetics": {
      "zones": [
        "MSTR_Z1",
        "MSTR_Z2"
      ],
      "recommended_time": [
        "midday"
      ],
      "tone_match": "Urbano-institucional — highway con skyline para claims de distribución/presencia. Torre Brickell para nivel B2B.",
      "copy_anchors": [
        "distribución desde el corazón de Miami",
        "donde los profesionales eligen calidad",
        "operando en el mercado más exigente de Florida"
      ]
    }
  },
  "shooting_context": {
    "collection_type": "drive-by / from vehicle",
    "notes": "La mayoría de las imágenes son tomas desde el interior del carro en movimiento. Esto les da un carácter de 'ciudad vivida desde adentro' — auténtico para audiencia ES-FL que reconoce estas vías. Para uso en contenido: crop agresivo para eliminar el tablero/capó del carro, o usarlo intencionalmente para el POV effect.",
    "pov_effect": "El marco del carro visible puede ser un elemento creativo intencional para Reels/Stories — 'traveling through Miami' narrative."
  },
  "reference_photos": {
    "path": "locations/assets/MiamiStreets/",
    "total": 9,
    "files": {
      "Z1_i95_highway": [
        "locations/assets/MiamiStreets/ms_i95_brickell_metromover_01.jpeg",
        "locations/assets/MiamiStreets/ms_i95_downtown_cranes_01.jpeg",
        "locations/assets/MiamiStreets/ms_i95_rickenbacker_sign_01.jpeg"
      ],
      "Z2_brickell_luxury": [
        "locations/assets/MiamiStreets/ms_brickell_towers_luxury_01.jpeg"
      ],
      "Z3_coconut_grove": [
        "locations/assets/MiamiStreets/ms_coconutgrove_trolley_01.jpeg",
        "locations/assets/MiamiStreets/ms_coconutgrove_marina_01.jpeg",
        "locations/assets/MiamiStreets/ms_coconutgrove_related_01.jpeg",
        "locations/assets/MiamiStreets/ms_boulevard_royal_palms_01.jpeg",
        "locations/assets/MiamiStreets/ms_residential_palm_street_01.jpeg"
      ]
    },
    "source": "iPhone, desde interior de vehículo + a pie en Coconut Grove",
    "alpha_processed": false,
    "note": "Fotos de locación/escena — alpha removal no aplica"
  },
  "last_updated": "2026-03-15",
  "asset_coverage": "partial — Z1 14/18 assets, Z3 3/7 assets"
}